{"cfg":{"name":"Tournoi Handball","date":"2026-06-27","start":"10:00","end":"18:00","ps":"12:45","pe":"13:30","dur":10,"gap":8,"fields":2,"poolsMode":"3","ptsW":3,"ptsD":2,"ptsL":1,"mainN":"auto","mainFields":"all","consolFields":"all","poolFmt":"single","poolRandomCount":2,"koFmt":"same","thirdPlace":"no"},"teams":[{"id":"3s2011i","name":"Rampillon","tel":"0616229241"},{"id":"49wmykc","name":"Les filets rafistolés","tel":"0648687661"},{"id":"62agwea","name":"Asture ye soif","tel":"0789543985"},{"id":"r0zvw9x","name":"Les Pères & Fils","tel":"0627256608"},{"id":"himix7q","name":"Les Parents","tel":"0646311572"},{"id":"eeddlaq","name":"FC Tourillon","tel":"0615364711"},{"id":"vc0e8tf","name":"Les soifards","tel":"0636073716"},{"id":"j07u4p2","name":"La brigade du but","tel":"0644256539"},{"id":"191l61b","name":"Les routiers","tel":"0630644143"},{"id":"cxmogae","name":"Les fous du Roy","tel":"0616685116"},{"id":"58h78u3","name":"Ça passe ou ça casse","tel":"0607083613"}],"pools":[[{"id":"himix7q","name":"Les Parents","tel":"0646311572"},{"id":"vc0e8tf","name":"Les soifards","tel":"0636073716"},{"id":"j07u4p2","name":"La brigade du but","tel":"0644256539"},{"id":"191l61b","name":"Les routiers","tel":"0630644143"}],[{"id":"r0zvw9x","name":"Les Pères & Fils","tel":"0627256608"},{"id":"58h78u3","name":"Ça passe ou ça casse","tel":"0607083613"},{"id":"3s2011i","name":"Rampillon","tel":"0616229241"},{"id":"cxmogae","name":"Les fous du Roy","tel":"0616685116"}],[{"id":"49wmykc","name":"Les filets rafistolés","tel":"0648687661"},{"id":"62agwea","name":"Asture ye soif","tel":"0789543985"},{"id":"eeddlaq","name":"FC Tourillon","tel":"0615364711"}]],"matches":[{"id":"ec6ex4e","phase":"pool","pool":0,"home":"himix7q","away":"vc0e8tf","homeScore":6,"awayScore":5,"played":true,"time":600,"field":1,"referee":"Flavie"},{"id":"ng8fa6n","phase":"pool","pool":0,"home":"j07u4p2","away":"191l61b","homeScore":10,"awayScore":9,"played":true,"time":600,"field":2,"referee":"Christophe"},{"id":"b1bds51","phase":"pool","pool":1,"home":"r0zvw9x","away":"58h78u3","homeScore":5,"awayScore":3,"played":true,"time":618,"field":1,"referee":"Jules"},{"id":"g0dcxo6","phase":"pool","pool":1,"home":"3s2011i","away":"cxmogae","homeScore":3,"awayScore":6,"played":true,"time":618,"field":2,"referee":"Benoit"},{"id":"8bew1nx","phase":"pool","pool":2,"home":"49wmykc","away":"62agwea","homeScore":6,"awayScore":4,"played":true,"time":636,"field":1,"referee":"Chloé"},{"id":"rdoj152","phase":"pool","pool":0,"home":"himix7q","away":"j07u4p2","homeScore":6,"awayScore":5,"played":true,"time":636,"field":2,"referee":"Popoche"},{"id":"9qnehtr","phase":"pool","pool":0,"home":"vc0e8tf","away":"191l61b","homeScore":4,"awayScore":9,"played":true,"time":654,"field":1,"referee":"Chloé"},{"id":"4qzhjyv","phase":"pool","pool":2,"home":"49wmykc","away":"eeddlaq","homeScore":5,"awayScore":10,"played":true,"time":654,"field":2,"referee":"Serge"},{"id":"f5rd786","phase":"pool","pool":1,"home":"r0zvw9x","away":"3s2011i","homeScore":8,"awayScore":1,"played":true,"time":672,"field":1,"referee":"Laurie"},{"id":"9h3k881","phase":"pool","pool":1,"home":"58h78u3","away":"cxmogae","homeScore":8,"awayScore":8,"played":true,"time":672,"field":2,"referee":"Christophe"},{"id":"n2z9x37","phase":"pool","pool":0,"home":"himix7q","away":"191l61b","homeScore":4,"awayScore":10,"played":true,"time":690,"field":1,"referee":"Benoit"},{"id":"hixd6fu","phase":"pool","pool":0,"home":"vc0e8tf","away":"j07u4p2","homeScore":2,"awayScore":10,"played":true,"time":690,"field":2,"referee":"Pierre"},{"id":"5pr8vxu","phase":"pool","pool":2,"home":"62agwea","away":"eeddlaq","homeScore":3,"awayScore":5,"played":true,"time":708,"field":1,"referee":"Chloé"},{"id":"io8h57l","phase":"pool","pool":1,"home":"r0zvw9x","away":"cxmogae","homeScore":9,"awayScore":8,"played":true,"time":708,"field":2,"referee":"Martin"},{"id":"zgx0b2w","phase":"pool","pool":1,"home":"58h78u3","away":"3s2011i","homeScore":null,"awayScore":null,"played":false,"time":726,"field":1,"referee":"Jules"},{"id":"n1l6h2r","phase":"main","pool":0,"home":"191l61b","away":"j07u4p2","homeScore":null,"awayScore":null,"played":false,"time":744,"field":1},{"id":"mzmziib","phase":"consol","pool":1,"home":"himix7q","away":"vc0e8tf","homeScore":null,"awayScore":null,"played":false,"time":744,"field":2},{"id":"gskgs4t","phase":"main","pool":0,"home":"191l61b","away":"r0zvw9x","homeScore":null,"awayScore":null,"played":false,"time":810,"field":1},{"id":"625mxul","phase":"consol","pool":1,"home":"himix7q","away":"58h78u3","homeScore":null,"awayScore":null,"played":false,"time":810,"field":2},{"id":"rtjq32d","phase":"main","pool":0,"home":"191l61b","away":"cxmogae","homeScore":null,"awayScore":null,"played":false,"time":828,"field":1},{"id":"8uot9by","phase":"consol","pool":1,"home":"himix7q","away":"3s2011i","homeScore":null,"awayScore":null,"played":false,"time":828,"field":2},{"id":"sgxh0b0","phase":"main","pool":0,"home":"191l61b","away":"eeddlaq","homeScore":null,"awayScore":null,"played":false,"time":846,"field":1},{"id":"80qltsk","phase":"main","pool":0,"home":"191l61b","away":"49wmykc","homeScore":null,"awayScore":null,"played":false,"time":846,"field":2},{"id":"8oh9ss3","phase":"consol","pool":1,"home":"himix7q","away":"62agwea","homeScore":null,"awayScore":null,"played":false,"time":864,"field":1},{"id":"233ke6g","phase":"consol","pool":1,"home":"vc0e8tf","away":"58h78u3","homeScore":null,"awayScore":null,"played":false,"time":864,"field":2},{"id":"e2zc1h2","phase":"main","pool":0,"home":"j07u4p2","away":"r0zvw9x","homeScore":null,"awayScore":null,"played":false,"time":882,"field":1},{"id":"33usl1x","phase":"main","pool":0,"home":"j07u4p2","away":"cxmogae","homeScore":null,"awayScore":null,"played":false,"time":882,"field":2},{"id":"h9r4t6k","phase":"consol","pool":1,"home":"vc0e8tf","away":"3s2011i","homeScore":null,"awayScore":null,"played":false,"time":900,"field":1},{"id":"2qguk64","phase":"main","pool":0,"home":"j07u4p2","away":"eeddlaq","homeScore":null,"awayScore":null,"played":false,"time":900,"field":2},{"id":"vn3stky","phase":"main","pool":0,"home":"j07u4p2","away":"49wmykc","homeScore":null,"awayScore":null,"played":false,"time":918,"field":1},{"id":"pih9c5p","phase":"consol","pool":1,"home":"vc0e8tf","away":"62agwea","homeScore":null,"awayScore":null,"played":false,"time":918,"field":2},{"id":"8r1x0x4","phase":"consol","pool":1,"home":"58h78u3","away":"3s2011i","homeScore":null,"awayScore":null,"played":false,"time":936,"field":1},{"id":"6wjiyno","phase":"main","pool":0,"home":"cxmogae","away":"r0zvw9x","homeScore":null,"awayScore":null,"played":false,"time":936,"field":2},{"id":"wmmy92a","phase":"main","pool":0,"home":"r0zvw9x","away":"eeddlaq","homeScore":null,"awayScore":null,"played":false,"time":954,"field":1},{"id":"snj1rb4","phase":"consol","pool":1,"home":"58h78u3","away":"62agwea","homeScore":null,"awayScore":null,"played":false,"time":954,"field":2},{"id":"r6tzgn2","phase":"main","pool":0,"home":"r0zvw9x","away":"49wmykc","homeScore":null,"awayScore":null,"played":false,"time":972,"field":1},{"id":"dnswi47","phase":"main","pool":0,"home":"cxmogae","away":"eeddlaq","homeScore":null,"awayScore":null,"played":false,"time":972,"field":2},{"id":"fd28014","phase":"consol","pool":1,"home":"3s2011i","away":"62agwea","homeScore":null,"awayScore":null,"played":false,"time":990,"field":1},{"id":"wdbx2ux","phase":"main","pool":0,"home":"cxmogae","away":"49wmykc","homeScore":null,"awayScore":null,"played":false,"time":990,"field":2},{"id":"dzc6p5z","phase":"main","pool":0,"home":"49wmykc","away":"eeddlaq","homeScore":null,"awayScore":null,"played":false,"time":1008,"field":1},{"id":"i093wyc","phase":"main_3rd","pool":0,"home":"TBD","away":"TBD","homeScore":null,"awayScore":null,"played":false,"time":1026,"field":1},{"id":"9vuek5v","phase":"main_final","pool":0,"home":"TBD","away":"TBD","homeScore":null,"awayScore":null,"played":false,"time":1044,"field":1},{"id":"jggwmq1","phase":"consol_3rd","pool":0,"home":"TBD","away":"TBD","homeScore":null,"awayScore":null,"played":false,"time":1008,"field":1},{"id":"slzqgpr","phase":"consol_final","pool":0,"home":"TBD","away":"TBD","homeScore":null,"awayScore":null,"played":false,"time":1026,"field":1}],"arbitres":["Flavie","Chloé","Laurie","Jules","Serge","Popoche","Pierre","Martin","Benoit","Christophe"],"finalsValidated":false,"ts":1782554461341,"tickerMsg":"PENSEZ A VOUS HYDRATER !"}